{
  "homeInfo": {
    "title": "首页",
    "href": "welcome"
  },
  "logoInfo": {
    "title": "AYNU",
    "image": "images/aynu.png",
    "href": "index"
  },
  "menuInfo": [
    {
      "title": "常规管理",
      "icon": "fa fa-address-book",
      "href": "",
      "target": "_self",
      "child": [
        {
          "title": "查看公告",
          "href": "notice/UserView",
          "icon": "fa fa-bullhorn",
          "target": "_self"
        },
        {
          "title": "查看成员",
          "href": "student/listReadOnly",
          "icon": "layui-icon layui-icon-user",
          "target": "_self"
        },
        {
          "title": "团队",
          "href": "",
          "icon": "layui-icon layui-icon-chart-screen",
          "target": "_self",
          "child": [
            {
              "title": "团队审核",
              "href": "team",
              "icon": "fa fa-tachometer",
              "target": "_self"
            },
            {
              "title": "查看团队",
              "href": "team/allPassTeam",
              "icon": "fa fa-tachometer",
              "target": "_self"
            }
          ]
        },
        {
          "title": "查看导师",
          "href": "teacher",
          "icon": "layui-icon layui-icon-username",
          "target": "_self"
        },
        {
          "title": "团队成果",
          "href": "",
          "icon": "fa fa-trophy",
          "target": "_self",
          "child": [
            {
              "title": "成果审核",
              "href": "project",
              "icon": "fa fa-tachometer",
              "target": "_self"
            },
            {
              "title": "查看成果",
              "href": "project/allPassProject",
              "icon": "fa fa-tachometer",
              "target": "_self"
            }
          ]
        }
      ]
    }

  ]
}